sapextractor/__init__.py
sapextractor/factory.py
sapextractor/main.py
sapextractor/algo/__init__.py
sapextractor/algo/factory.py
sapextractor/algo/ap_ar/__init__.py
sapextractor/algo/ap_ar/ap_ar_common.py
sapextractor/algo/ap_ar/cli.py
sapextractor/algo/ap_ar/doc_flow_transactions_dataframe.py
sapextractor/algo/ap_ar/doc_flow_transactions_log.py
sapextractor/algo/ap_ar/document_flow_dataframe.py
sapextractor/algo/ap_ar/document_flow_log.py
sapextractor/algo/ap_ar/factory.py
sapextractor/algo/ap_ar/freq_doc_types.py
sapextractor/algo/ap_ar/graph_retrieval_util.py
sapextractor/algo/ap_ar/obj_centr_log.py
sapextractor/algo/ap_ar/single_doc_transactions_dataframe.py
sapextractor/algo/ap_ar/single_doc_transactions_log.py
sapextractor/algo/o2c/__init__.py
sapextractor/algo/o2c/change_activities_util.py
sapextractor/algo/o2c/cli.py
sapextractor/algo/o2c/factory.py
sapextractor/algo/o2c/freq_client.py
sapextractor/algo/o2c/graph_retrieval_util.py
sapextractor/algo/o2c/o2c_1d_dataframe_extractor.py
sapextractor/algo/o2c/o2c_1d_log_extractor.py
sapextractor/algo/o2c/o2c_common.py
sapextractor/algo/o2c/obj_centr_log.py
sapextractor/algo/o2c/payment_part.py
sapextractor/algo/p2p/__init__.py
sapextractor/algo/p2p/cli.py
sapextractor/algo/p2p/factory.py
sapextractor/algo/p2p/freq_doc_types.py
sapextractor/algo/p2p/obj_centr_log.py
sapextractor/algo/p2p/p2p_1d_dataframe.py
sapextractor/algo/p2p/p2p_1d_log.py
sapextractor/algo/p2p/p2p_common.py
sapextractor/algo/p2p/tab_processing/__init__.py
sapextractor/algo/p2p/tab_processing/bkpf_processing.py
sapextractor/algo/p2p/tab_processing/bsak_processing.py
sapextractor/algo/p2p/tab_processing/eban_processing.py
sapextractor/algo/p2p/tab_processing/ekbe_processing.py
sapextractor/algo/p2p/tab_processing/ekko_processing.py
sapextractor/algo/p2p/tab_processing/ekpo_processing.py
sapextractor/algo/p2p/tab_processing/rbkp_processing.py
sapextractor/algo/p2p/tab_processing/rseg_processing.py
sapextractor/database_connection/__init__.py
sapextractor-0.0.22.dist-info/LICENSE
sapextractor-0.0.22.dist-info/METADATA
sapextractor-0.0.22.dist-info/WHEEL
sapextractor-0.0.22.dist-info/top_level.txt
sapextractor-0.0.22.dist-info/RECORD
