Metadata-Version: 2.1
Name: sapextractor
Version: 0.0.22
Summary: SAP Extractor
Home-page: http://www.pm4py.org
Author: PADS
Author-email: alessandro.berti89@gmail.com
License: GPL 3.0
Platform: UNKNOWN
Requires-Dist: pm4py (>=2.2.2)
Requires-Dist: pm4pymdl (>=0.0.45)
Requires-Dist: stringdist
Requires-Dist: cx-Oracle
Requires-Dist: plantuml
Requires-Dist: frozendict
Requires-Dist: pymssql
